pyalgo_tools/__init__.py
pyalgo_tools/py.typed
pyalgo_tools-0.1.5.dist-info/METADATA
pyalgo_tools-0.1.5.dist-info/WHEEL
pyalgo_tools-0.1.5.dist-info/licenses/LICENSE
pyalgo_tools-0.1.5.dist-info/RECORD
