Metadata-Version: 2.4
Name: pyalgo-tools
Version: 0.1.5
Summary: Algorithm of etc.
Project-URL: homepage, https://github.com/SaitoTsutomu/pyalgo-tools
Author-email: Saito Tsutomu <tsutomu7@hotmail.co.jp>
License: Apache-2.0
License-File: LICENSE
Classifier: Development Status :: 1 - Planning
Classifier: License :: OSI Approved :: Apache Software License
Classifier: Programming Language :: Python
Classifier: Topic :: Scientific/Engineering
Classifier: Topic :: Software Development
Requires-Python: >=3.12
Requires-Dist: networkx>=3.4.2
Requires-Dist: numpy>=2.2.1
Requires-Dist: pandas>=2.2.3
Requires-Dist: scipy>=1.15.0
